{
  "audit_config": {
    "max_iter_eq": 10,
    "nb": 120,
    "p_init": 0.725,
    "tol_eq": null
  },
  "audit_fit": [
    {
      "gap": -0.2299876566042478,
      "loss_contribution": 0.31736593314188044,
      "model": 5.54998282533772,
      "moment": "aggregate_mean_occupied_rooms_18_85",
      "target": 5.779970481941968,
      "weight": 6.0
    },
    {
      "gap": -0.016501102841100873,
      "loss_contribution": 0.005445727899451746,
      "model": 0.17149889715889913,
      "moment": "childless_rate",
      "target": 0.188,
      "weight": 20.0
    },
    {
      "gap": 0.018248574415282603,
      "loss_contribution": 0.004662146554661495,
      "model": 0.6826832444152826,
      "moment": "housing_increment_0to1",
      "target": 0.66443467,
      "weight": 14.0
    },
    {
      "gap": 0.1836062936882501,
      "loss_contribution": 5.393803373109752,
      "model": 0.9478672636882501,
      "moment": "old_age_own_rate",
      "target": 0.76426097,
      "weight": 160.0
    },
    {
      "gap": -1.201921522280542,
      "loss_contribution": 1.1556922765769402,
      "model": 1.028539257719458,
      "moment": "old_nonhousing_wealth_to_income_median_6575",
      "target": 2.23046078,
      "weight": 0.8
    },
    {
      "gap": 0.24414313064074933,
      "loss_contribution": 0.11921173647813199,
      "model": 1.2515926506407493,
      "moment": "old_parent_childless_nonhousing_wealth_to_income_gap_6575",
      "target": 1.00744952,
      "weight": 2.0
    },
    {
      "gap": 0.060160670254631704,
      "loss_contribution": 0.16286878104689376,
      "model": 0.22782234025463172,
      "moment": "own_family_gap",
      "target": 0.16766167,
      "weight": 45.0
    },
    {
      "gap": 0.07771478591760184,
      "loss_contribution": 0.6039587950218686,
      "model": 0.6531871959176019,
      "moment": "own_rate",
      "target": 0.57547241,
      "weight": 100.0
    },
    {
      "gap": -0.09199699152761942,
      "loss_contribution": 0.6770757160106303,
      "model": 0.24916909847238056,
      "moment": "own_rate_2534",
      "target": 0.34116609,
      "weight": 80.0
    },
    {
      "gap": -0.47575369998832784,
      "loss_contribution": 2.7160989966310063,
      "model": 1.943008030011672,
      "moment": "prime30_55_childless_owner_minus_renter_mean_rooms",
      "target": 2.41876173,
      "weight": 12.0
    },
    {
      "gap": 0.144964598144669,
      "loss_contribution": 0.5253683678811343,
      "model": 0.741095718144669,
      "moment": "prime30_55_childless_owner_share_rooms_ge6",
      "target": 0.59613112,
      "weight": 25.0
    },
    {
      "gap": 0.47764677105545283,
      "loss_contribution": 1.368878627398201,
      "model": 4.282934871055453,
      "moment": "prime30_55_childless_renter_mean_rooms",
      "target": 3.8052881,
      "weight": 6.0
    },
    {
      "gap": -0.14401016991374765,
      "loss_contribution": 0.16591143230869176,
      "model": 0.22368938889625234,
      "moment": "prime30_55_parent_3plus_minus_1to2_mean_rooms",
      "target": 0.36769955881,
      "weight": 8.0
    },
    {
      "gap": 0.0632736467763253,
      "loss_contribution": 0.08007108752750362,
      "model": 1.9812736467763252,
      "moment": "tfr",
      "target": 1.918,
      "weight": 20.0
    },
    {
      "gap": 0.3602341239168856,
      "loss_contribution": 1.557223488409993,
      "model": 0.5394596839168856,
      "moment": "young_childless_renter_liquid_wealth_to_annual_gross_income_2535",
      "target": 0.17922556,
      "weight": 12.0
    }
  ],
  "audit_wall_seconds": 682.9779012479994,
  "case": 0,
  "elapsed_sec": 682.9466775459996,
  "full_old_nonlocation_loss": 256.49017593859554,
  "income_process_fingerprint": "5b6875a240e82073e515a291469e2d259c35bb01ca63cabfb10b639700db5daf",
  "label": "current_pinit_hi",
  "loss_gap_vs_stored": 0.07361578602415264,
  "market_residual": 0.00010717984736698594,
  "moments": {
    "aggregate_mean_occupied_rooms_18_85": 5.54998282533772,
    "aggregate_own_rate": 0.6779617810920969,
    "childless_rate": 0.17149889715889913,
    "housing_increment_0to1": 0.6826832444152826,
    "housing_increment_1to2": -0.9839303080969497,
    "housing_user_cost_share": 0.22463725523457234,
    "liquid_wealth_to_income": -0.12135904675003119,
    "market_residual": 0.00010717984736698594,
    "mean_age_first_birth": 30.549440962214806,
    "mean_completed_fertility": 0.9906368233881626,
    "old_age_own_rate": 0.9478672636882501,
    "old_age_parent_childless_gap": 0.03370975436924484,
    "old_age_parent_childless_gap_6575": 0.03370975436924484,
    "old_minus_young_owner_rate_6575_2534": 0.6986981652158696,
    "old_nonhousing_wealth_to_income_6575": 1.6073559384939011,
    "old_nonhousing_wealth_to_income_median_6575": 1.028539257719458,
    "old_owner_rate": 0.9478672636882501,
    "old_parent_childless_nonhousing_wealth_to_income_gap_6575": 1.2515926506407493,
    "old_parent_childless_nonhousing_wealth_to_income_median_gap_6575": 1.028539257719458,
    "old_parent_childless_total_wealth_to_income_gap_6575": 3.659501940490216,
    "old_parent_childless_total_wealth_to_income_median_gap_6575": 3.667633162096311,
    "old_total_wealth_to_income_6575": 10.055396585866605,
    "old_total_wealth_to_income_median_6575": 9.433023777138189,
    "own_family_gap": 0.22782234025463172,
    "own_gap_newparent_nonparent_3055": 0.22782234025463172,
    "own_rate": 0.6531871959176019,
    "own_rate_2534": 0.24916909847238056,
    "own_rate_3055": 0.6531871959176019,
    "own_rate_3544": 0.5546136973141244,
    "own_rate_newparents_3055": 0.6249701847604767,
    "own_rate_nonparents_3055": 0.397147844505845,
    "owner_neg_liquid_share_2534": 0.5892633855269402,
    "parity_share_0": 0.17149889715889913,
    "parity_share_1": 0.6663653822940389,
    "parity_share_2plus": 0.1621357205470619,
    "prime30_55_childless_owner_mean_rooms": 6.225942901067125,
    "prime30_55_childless_owner_minus_renter_mean_rooms": 1.943008030011672,
    "prime30_55_childless_owner_share_rooms_ge6": 0.741095718144669,
    "prime30_55_childless_renter_mean_rooms": 4.282934871055453,
    "prime30_55_childless_renter_share_rooms_ge6": 0.06308270819354385,
    "prime30_55_parent_3plus_minus_1to2_mean_rooms": 0.22368938889625234,
    "prime30_55_parent_owner_minus_renter_mean_rooms": 1.9838759594879383,
    "prime_childless_owner_median_rooms": 6.0,
    "prime_childless_owner_minus_renter_rooms": 1.8748941227420675,
    "prime_childless_renter_median_rooms": 4.1251058772579325,
    "renter25_45_all_cap_share": 0.18999875596543617,
    "tfr": 1.9812736467763252,
    "wealth_to_income": 1.0170327621649267,
    "young_all_liquid_wealth_to_annual_gross_income_2530": 0.24605968338022258,
    "young_all_liquid_wealth_to_annual_gross_income_2530_median": 0.2235362463096784,
    "young_childless_liquid_wealth_to_annual_gross_income_2535": 0.222396063206247,
    "young_childless_liquid_wealth_to_annual_gross_income_2535_median": 0.2235362463096784,
    "young_childless_renter_liquid_wealth_to_annual_gross_income_2535": 0.5394596839168856,
    "young_childless_renter_liquid_wealth_to_annual_gross_income_2535_median": 0.28162794233456406,
    "young_liquid_wealth_to_income": 0.2019562312408085,
    "young_owner_rate": 0.24916909847238056
  },
  "p_eq": [
    0.689651829252508
  ],
  "rank_loss": 14.853636485996738,
  "status": "ok",
  "stored_loss": 14.780020699972585,
  "stored_residual": 2.906086971430419e-05,
  "strict_converged": false,
  "theta": {
    "H0": 9.999672059746388,
    "alpha_cons": 0.6731064483929385,
    "beta": 0.8411423842686492,
    "c_bar_0": 1.28,
    "c_bar_n": 0.4559787014242588,
    "chi": 1.15,
    "h_bar_0": 1.0,
    "h_bar_jump": 1.4758939442666474,
    "h_bar_n": 0.984106767291167,
    "kappa_fert": 1.8906304000000005,
    "psi_child": 0.26907999999999993,
    "tenure_choice_kappa": 0.0,
    "theta0": 0.1318301350511569,
    "theta_n": 0.7679202774006243
  },
  "timings": {
    "accepted": false,
    "bellman_full": 7.017981406000217,
    "bellman_mode": "full_only",
    "best_eq_error": 0.00010717984736698594,
    "convergence_reason": "max_iter",
    "damped_final_eq_error": 0.00041796214678507457,
    "distribution": 21.479531816999952,
    "final_eq_error": 0.00010717984736698594,
    "income_process": "markov",
    "iterations_completed": 10,
    "markov_income_solve_time": 97.00656654600152,
    "n_dist": 1,
    "n_eval": 0,
    "n_full": 1,
    "scalar_market_refine": {
      "best_excess": 0.0005947825634047277,
      "best_metric": 0.00010717984736698594,
      "best_price": 0.689651829252508,
      "bracket_found": true,
      "expansions": 0,
      "initial_price": 0.6899720054278443,
      "iterations": 16,
      "method": "brent",
      "price_evaluation_time_sec": 557.3170366360027,
      "price_evaluations": 18,
      "used": true
    },
    "strict_converged": false
  },
  "tol_eq": 0.0001
}